./.gitignore
./PKG-INFO
./activities.py
./boot-demo.sh
./demo-image.png
./pyproject.toml
./readme.md
./server.py
./worker.py
./workflows.py
./assets/claude-mcp-invoice-status.png
./assets/claude-mcp-invoice-submission.png
./assets/claude-mcp-submit-approve-status.png
./assets/interactive-workflows-with-agentic-power.png
./samples/invoice_acme.json
mseep_temporal_invoice_mcp-0.1.2.dist-info/METADATA
mseep_temporal_invoice_mcp-0.1.2.dist-info/WHEEL
mseep_temporal_invoice_mcp-0.1.2.dist-info/entry_points.txt
mseep_temporal_invoice_mcp-0.1.2.dist-info/RECORD
