Metadata-Version: 2.4
Name: mseep-temporal-invoice-mcp
Version: 0.1.2
Summary: Invoice processing demo using Temporal workflows and MCP (Model Context Protocol)
Project-URL: Homepage, https://github.com/Aslan11/temporal-invoice-mcp
Project-URL: Repository, https://github.com/Aslan11/temporal-invoice-mcp.git
Project-URL: Issues, https://github.com/Aslan11/temporal-invoice-mcp/issues
Author-email: mseep <support@skydeck.ai>
License: MIT
Keywords: automation,invoice,mcp,temporal,workflow
Classifier: Development Status :: 3 - Alpha
Classifier: Intended Audience :: Developers
Classifier: License :: OSI Approved :: MIT License
Classifier: Operating System :: OS Independent
Classifier: Programming Language :: Python :: 3
Classifier: Programming Language :: Python :: 3.10
Classifier: Programming Language :: Python :: 3.11
Classifier: Programming Language :: Python :: 3.12
Classifier: Programming Language :: Python :: 3.13
Classifier: Topic :: Office/Business :: Financial
Classifier: Topic :: Software Development :: Libraries :: Python Modules
Requires-Python: >=3.10
Requires-Dist: fastmcp>=0.1.0
Requires-Dist: temporalio>=1.0.0
Provides-Extra: dev
Requires-Dist: black>=23.0.0; extra == 'dev'
Requires-Dist: flake8>=6.0.0; extra == 'dev'
Requires-Dist: isort>=5.12.0; extra == 'dev'
Requires-Dist: mypy>=1.0.0; extra == 'dev'
Requires-Dist: pytest-asyncio>=0.21.0; extra == 'dev'
Requires-Dist: pytest>=7.0.0; extra == 'dev'
